Workbook

Sheet Sheet4
D7: CLEAR RESULT
D8: Percentage of passing | G8: =AVERAGE(Sheet5!K3:K7) -> 77.1
D9: No of students passed | G9: =COUNTIF(Sheet5!L3:L7,"PASS") -> 4 | Z9: Check No | AA9: Preview check 6 digits | AB9: Len() with rept() with &
D10: No of students failed | G10: =COUNTIF(Sheet5!L3:L7,"FAIL") -> 1 | J10: STRING | K10: PROPER() | L10: UPPER() | M10: LOWER() | N10: TRIM() | T10: Name | U10: Points | V10: REPT() | Z10: 111556 | AA10: 111556 | AB10: =REPT("0",6-LEN(Z10))&Z10 -> 111556
D11: No of students with Grade A | G11: =COUNTIF(Sheet5!M3:M7,"A") -> 3 | J11: TodAy Is Not GoOdDAy | K11: =PROPER(J11) -> Today Is Not Goodday | L11: =UPPER(J11) -> TODAY IS NOT GOODDAY | M11: =LOWER(J11) -> today is not goodday | N11: =TRIM(J11) -> TodAy Is Not GoOdDAy | T11: SOOMIN | U11: 2 | V11: =REPT(T11,U11) -> SOOMINSOOMIN | Z11: 5642 | AA11: 5642 | AB11: =REPT("0",6-LEN(Z11))&Z11 -> 005642
D12: No of students with Grade B | G12: =COUNTIF(Sheet5!M3:M7,"B") -> 2 | J12: AyIshA IS aCtINg WEiRd | K12: =PROPER(J12) -> Ayisha Is Acting Weird | L12: =UPPER(J12) -> AYISHA IS ACTING WEIRD | M12: =LOWER(J12) -> ayisha is acting weird | N12: =TRIM(J12) -> AyIshA IS aCtINg WEiRd | T12: DONGWOOK | U12: 3 | V12: =REPT(T12,U12) -> DONGWOOKDONGWOOKDONGWOOK | Z12: 112568 | AA12: 112568 | AB12: =REPT("0",6-LEN(Z12))&Z12 -> 112568
D13: No of students with Grade C | G13: =COUNTIF(Sheet5!M3:M7,"C") -> 0 | T13: JUNYOUNG | U13: 4 | V13: =REPT(T13,U13) -> JUNYOUNGJUNYOUNGJUNYOUNGJUNYOUNG | Z13: 35 | AA13: 35 | AB13: =REPT("0",6-LEN(Z13))&Z13 -> 000035
T14: SUNGHYOON | U14: 5 | V14: =REPT(T14,U14) -> SUNGHYOONSUNGHYOONSUNGHYOONSUNGHYOONSUNGHYOON | Z14: 29 | AA14: 29 | AB14: =REPT("0",6-LEN(Z14))&Z14 -> 000029
J15: STRING | K15: T() | L15: N() | M15: VALUE() | N15: ISNUMBER() | T15: REHYON | U15: 6 | V15: =REPT(T15,U15) -> REHYONREHYONREHYONREHYONREHYONREHYON | Z15: 23564 | AA15: 23564 | AB15: =REPT("0",6-LEN(Z15))&Z15 -> 023564
J16: 7584 | K16: =T(J16) | L16: =N(J16) -> 7584 | M16: =VALUE(J16) -> 7584 | N16: =ISNUMBER(J16) -> TRUE | T16: AH-YEON | U16: 7 | V16: =REPT(T16,U16) -> AH-YEONAH-YEONAH-YEONAH-YEONAH-YEONAH-YEONAH-YEON | Z16: 7832 | AA16: 7832 | AB16: =REPT("0",6-LEN(Z16))&Z16 -> 007832
J17: 7896 | K17: =T(J17) | L17: =N(J17) -> 7896 | M17: =VALUE(J17) -> 7896 | N17: =ISNUMBER(J17) -> TRUE | T17: KIM TAEHYUNG | U17: 7 | V17: =REPT(T17,U17) -> KIM TAEHYUNGKIM TAEHYUNGKIM TAEHYUNGKIM TAEHYUNGKIM TAEHYUNGKIM TAEHYUNGKIM TAEHYUNG
J18: 2358 | K18: =T(J18) | L18: =N(J18) -> 2358 | M18: =VALUE(J18) -> 2358 | N18: =ISNUMBER(J18) -> TRUE | T18: MMMMMM | U18: 8 | V18: =REPT(T18,U18) -> MMMMMMMMMMMMMMMMMMMMMMMMMMMMMMMMMMMMMMMMMMMMMMMM
J19: 2348 | K19: =T(J19) | L19: =N(J19) -> 2348 | M19: =VALUE(J19) -> 2348 | N19: =ISNUMBER(J19) -> TRUE | T19: MWEHEHEHEH | U19: 9 | V19: =REPT(T19,U19) -> MWEHEHEHEHMWEHEHEHEHMWEHEHEHEHMWEHEHEHEHMWEHEHEHEHMWEHEHEHEHMWEHEHEHEHMWEHEHEHEHMWEHEHEHEH

Sheet Sheet5
B2: Reg No | C2: Name | D2: Sub1 | E2: Sub2 | F2: Sub3 | G2: Sub4 | H2: Sub5 | I2: sub6 | J2: Total | K2: Avg | L2: Result(PASS/FAIL) | M2: Grade
A3: 1 | B3: 711 | C3: Shin Hari | D3: 75 | E3: 63 | F3: 88 | G3: 73 | H3: 83 | I3: 87 | J3: =SUM(D3:I3) -> 469 | K3: =AVERAGE(D3:I3) -> 78.166667 | L3: =IF(OR(D3<35,E3<35,F3<35,G3<35,H3<35,I3<35),"FAIL","PASS") -> PASS | M3: =IF(K3>75,"A","B") -> A
A4: 2 | B4: 722 | C4: Do-Dohee | D4: 96 | E4: 88 | F4: 97 | G4: 79 | H4: 96 | I4: 99 | J4: =SUM(D4:I4) -> 555 | K4: =AVERAGE(D4:I4) -> 92.5 | L4: =IF(OR(D4<35,E4<35,F4<35,G4<35,H4<35,I4<35),"FAIL","PASS") -> PASS | M4: =IF(K4>75,"A","B") -> A
A5: 3 | B5: 733 | C5: Ah-Yeon | D5: 82 | E5: 74 | F5: 44 | G5: 81 | H5: 74 | I5: 62 | J5: =SUM(D5:I5) -> 417 | K5: =AVERAGE(D5:I5) -> 69.5 | L5: =IF(OR(D5<35,E5<35,F5<35,G5<35,H5<35,I5<35),"FAIL","PASS") -> PASS | M5: =IF(K5>75,"A","B") -> B
A6: 4 | B6: 744 | C6: Dongwook | D6: 66 | E6: 84 | F6: 77 | G6: 93 | H6: 65 | I6: 77 | J6: =SUM(D6:I6) -> 462 | K6: =AVERAGE(D6:I6) -> 77 | L6: =IF(OR(D6<35,E6<35,F6<35,G6<35,H6<35,I6<35),"FAIL","PASS") -> PASS | M6: =IF(K6>75,"A","B") -> A
A7: 5 | B7: 755 | C7: Soomin | D7: 79 | E7: 30 | F7: 68 | G7: 88 | H7: 82 | I7: 63 | J7: =SUM(D7:I7) -> 410 | K7: =AVERAGE(D7:I7) -> 68.333333 | L7: =IF(OR(D7<35,E7<35,F7<35,G7<35,H7<35,I7<35),"FAIL","PASS") -> FAIL | M7: =IF(K7>75,"A","B") -> B

Sheet Sheet3
A1: Total Max Marks | C1: 600
A4: Reg No | B4: Name | C4: Physics | D4: Chemistry | E4: Mathematics | F4: Biology | G4: English | H4: Kannada | I4: Total Marks Obtained | J4: Average | K4: Grade | L4: Pass/Fail
A5: 1 | B5: Kim | C5: 75 | D5: 66 | E5: 88 | F5: 68 | G5: 90 | H5: 88 | I5: =SUM(Table2[[#This Row],[Column3]:[Column8]]) -> 475 | J5: =I5/$C$1*100 -> 79.166667 | K5: =IF(Table2[[#This Row],[Column10]]>75,"A","B") -> A | L5: =IF(OR(Table2[[#This Row],[Column3]]<35,Table2[[#This Row],[Column4]]<35,Table2[[#This Row],[Column5]]<35,Table2[[#This Row],[Column6]]<35,Table2[[#This Row],[Column7]]<35,Table2[[#This Row],[Column8]]<35),"FAIL","PASS") -> PASS
A6: 2 | B6: Dami | C6: 80 | D6: 72 | E6: 68 | F6: 84 | G6: 86 | H6: 53 | I6: =SUM(Table2[[#This Row],[Column3]:[Column8]]) -> 443 | J6: =I6/$C$1*100 -> 73.833333 | K6: =IF(Table2[[#This Row],[Column10]]>75,"A","B") -> B | L6: =IF(OR(Table2[[#This Row],[Column3]]<35,Table2[[#This Row],[Column4]]<35,Table2[[#This Row],[Column5]]<35,Table2[[#This Row],[Column6]]<35,Table2[[#This Row],[Column7]]<35,Table2[[#This Row],[Column8]]<35),"FAIL","PASS") -> PASS
A7: 3 | B7: Hyeri | C7: 66 | D7: 88 | E7: 49 | F7: 53 | G7: 73 | H7: 42 | I7: =SUM(Table2[[#This Row],[Column3]:[Column8]]) -> 371 | J7: =I7/$C$1*100 -> 61.833333 | K7: =IF(Table2[[#This Row],[Column10]]>75,"A","B") -> B | L7: =IF(OR(Table2[[#This Row],[Column3]]<35,Table2[[#This Row],[Column4]]<35,Table2[[#This Row],[Column5]]<35,Table2[[#This Row],[Column6]]<35,Table2[[#This Row],[Column7]]<35,Table2[[#This Row],[Column8]]<35),"FAIL","PASS") -> PASS
A8: 4 | B8: Song kang | C8: 45 | D8: 69 | E8: 52 | F8: 74 | G8: 85 | H8: 75 | I8: =SUM(Table2[[#This Row],[Column3]:[Column8]]) -> 400 | J8: =I8/$C$1*100 -> 66.666667 | K8: =IF(Table2[[#This Row],[Column10]]>75,"A","B") -> B | L8: =IF(OR(Table2[[#This Row],[Column3]]<35,Table2[[#This Row],[Column4]]<35,Table2[[#This Row],[Column5]]<35,Table2[[#This Row],[Column6]]<35,Table2[[#This Row],[Column7]]<35,Table2[[#This Row],[Column8]]<35),"FAIL","PASS") -> PASS
A9: 5 | B9: Teri | C9: 80 | D9: 75 | E9: 76 | F9: 64 | G9: 74 | H9: 73 | I9: =SUM(Table2[[#This Row],[Column3]:[Column8]]) -> 442 | J9: =I9/$C$1*100 -> 73.666667 | K9: =IF(Table2[[#This Row],[Column10]]>75,"A","B") -> B | L9: =IF(OR(Table2[[#This Row],[Column3]]<35,Table2[[#This Row],[Column4]]<35,Table2[[#This Row],[Column5]]<35,Table2[[#This Row],[Column6]]<35,Table2[[#This Row],[Column7]]<35,Table2[[#This Row],[Column8]]<35),"FAIL","PASS") -> PASS
A10: 6 | B10: Eunwoo | C10: 95 | D10: 90 | E10: 99 | F10: 92 | G10: 95 | H10: 99 | I10: =SUM(Table2[[#This Row],[Column3]:[Column8]]) -> 570 | J10: =I10/$C$1*100 -> 95 | K10: =IF(Table2[[#This Row],[Column10]]>75,"A","B") -> A | L10: =IF(OR(Table2[[#This Row],[Column3]]<35,Table2[[#This Row],[Column4]]<35,Table2[[#This Row],[Column5]]<35,Table2[[#This Row],[Column6]]<35,Table2[[#This Row],[Column7]]<35,Table2[[#This Row],[Column8]]<35),"FAIL","PASS") -> PASS
A11: 7 | B11: Rowoon | C11: 90 | D11: 88 | E11: 46 | F11: 51 | G11: 85 | H11: 63 | I11: =SUM(Table2[[#This Row],[Column3]:[Column8]]) -> 423 | J11: =I11/$C$1*100 -> 70.5 | K11: =IF(Table2[[#This Row],[Column10]]>75,"A","B") -> B | L11: =IF(OR(Table2[[#This Row],[Column3]]<35,Table2[[#This Row],[Column4]]<35,Table2[[#This Row],[Column5]]<35,Table2[[#This Row],[Column6]]<35,Table2[[#This Row],[Column7]]<35,Table2[[#This Row],[Column8]]<35),"FAIL","PASS") -> PASS
A12: 8 | B12: Moon Ka young | C12: 84 | D12: 68 | E12: 52 | F12: 85 | G12: 63 | H12: 82 | I12: =SUM(Table2[[#This Row],[Column3]:[Column8]]) -> 434 | J12: =I12/$C$1*100 -> 72.333333 | K12: =IF(Table2[[#This Row],[Column10]]>75,"A","B") -> B | L12: =IF(OR(Table2[[#This Row],[Column3]]<35,Table2[[#This Row],[Column4]]<35,Table2[[#This Row],[Column5]]<35,Table2[[#This Row],[Column6]]<35,Table2[[#This Row],[Column7]]<35,Table2[[#This Row],[Column8]]<35),"FAIL","PASS") -> PASS
A13: 9 | B13: Jeonghan | C13: 88 | D13: 77 | E13: 87 | F13: 74 | G13: 42 | H13: 74 | I13: =SUM(Table2[[#This Row],[Column3]:[Column8]]) -> 442 | J13: =I13/$C$1*100 -> 73.666667 | K13: =IF(Table2[[#This Row],[Column10]]>75,"A","B") -> B | L13: =IF(OR(Table2[[#This Row],[Column3]]<35,Table2[[#This Row],[Column4]]<35,Table2[[#This Row],[Column5]]<35,Table2[[#This Row],[Column6]]<35,Table2[[#This Row],[Column7]]<35,Table2[[#This Row],[Column8]]<35),"FAIL","PASS") -> PASS
A14: 10 | B14: Minho | C14: 46 | D14: 67 | E14: 90 | F14: 45 | G14: 85 | H14: 52 | I14: =SUM(Table2[[#This Row],[Column3]:[Column8]]) -> 385 | J14: =I14/$C$1*100 -> 64.166667 | K14: =IF(Table2[[#This Row],[Column10]]>75,"A","B") -> B | L14: =IF(OR(Table2[[#This Row],[Column3]]<35,Table2[[#This Row],[Column4]]<35,Table2[[#This Row],[Column5]]<35,Table2[[#This Row],[Column6]]<35,Table2[[#This Row],[Column7]]<35,Table2[[#This Row],[Column8]]<35),"FAIL","PASS") -> PASS
A15: 11 | B15: Jungsuk | C15: 85 | D15: 76 | E15: 74 | F15: 81 | G15: 74 | H15: 41 | I15: =SUM(Table2[[#This Row],[Column3]:[Column8]]) -> 431 | J15: =I15/$C$1*100 -> 71.833333 | K15: =IF(Table2[[#This Row],[Column10]]>75,"A","B") -> B | L15: =IF(OR(Table2[[#This Row],[Column3]]<35,Table2[[#This Row],[Column4]]<35,Table2[[#This Row],[Column5]]<35,Table2[[#This Row],[Column6]]<35,Table2[[#This Row],[Column7]]<35,Table2[[#This Row],[Column8]]<35),"FAIL","PASS") -> PASS
A16: 12 | B16: Hyungsik | C16: 90 | D16: 47 | E16: 55 | F16: 63 | G16: 65 | H16: 63 | I16: =SUM(Table2[[#This Row],[Column3]:[Column8]]) -> 383 | J16: =I16/$C$1*100 -> 63.833333 | K16: =IF(Table2[[#This Row],[Column10]]>75,"A","B") -> B | L16: =IF(OR(Table2[[#This Row],[Column3]]<35,Table2[[#This Row],[Column4]]<35,Table2[[#This Row],[Column5]]<35,Table2[[#This Row],[Column6]]<35,Table2[[#This Row],[Column7]]<35,Table2[[#This Row],[Column8]]<35),"FAIL","PASS") -> PASS
... A19: 15 | B19: Yumi | C19: 83 | D19: 77 | E19: 43 | F19: 44 | G19: 75 | H19: 84 | I19: =SUM(Table2[[#This Row],[Column3]:[Column8]]) -> 406 | J19: =I19/$C$1*100 -> 67.666667 | K19: =IF(Table2[[#This Row],[Column10]]>75,"A","B") -> B | L19: =IF(OR(Table2[[#This Row],[Column3]]<35,Table2[[#This Row],[Column4]]<35,Table2[[#This Row],[Column5]]<35,Table2[[#This Row],[Column6]]<35,Table2[[#This Row],[Column7]]<35,Table2[[#This Row],[Column8]]<35),"FAIL","PASS") -> PASS
S24: REALTIVE REFERENCE | Y24: ABSOLUTE REFERNCE | AD24: MIXED REFERNCE
Y25: MAX SCORE | Z25: 100
S26: Month | T26: Total income | U26: Total Expenses | V26: Net Income | Y26: Name | Z26: Grand Totals | AA26: Percentage | AD26: Multiplication table
S27: Jan | T27: 40000 | U27: 10000 | V27: =SUM(T27,U27) -> 50000 | Y27: Tom | Z27: 85 | AA27: =Table6[[#This Row],[Column2]]/$Z$25 -> 0.85 | AD27: Colum Header
S28: Feb | T28: 50000 | U28: 12000 | V28: =SUM(T28,U28) -> 62000 | Y28: James | Z28: 76 | AA28: =Table6[[#This Row],[Column2]]/$Z$25 -> 0.76 | AC28: Row Header | AE28: 1 | AF28: 2 | AG28: 3 | AH28: 4 | AI28: 5
S29: Mar | T29: 60000 | U29: 13000 | V29: =SUM(T29,U29) -> 73000 | Y29: Travis | Z29: 88 | AA29: =Table6[[#This Row],[Column2]]/$Z$25 -> 0.88 | AD29: 10 | AE29: =AE$28*$AD29 -> 10 | AF29: =AF$28*$AD29 -> 20 | AG29: =AG$28*$AD29 -> 30 | AH29: =AH$28*$AD29 -> 40 | AI29: =AI$28*$AD29 -> 50
S30: Apr | T30: 70000 | U30: 15000 | V30: =SUM(T30,U30) -> 85000 | Y30: Clara | Z30: 96 | AA30: =Table6[[#This Row],[Column2]]/$Z$25 -> 0.96 | AD30: 20 | AE30: =AE$28*$AD30 -> 20 | AF30: =AF$28*$AD30 -> 40 | AG30: =AG$28*$AD30 -> 60 | AH30: =AH$28*$AD30 -> 80 | AI30: =AI$28*$AD30 -> 100
S31: May | T31: 80000 | U31: 20000 | V31: =SUM(T31,U31) -> 100000 | Y31: Sara | Z31: 94 | AA31: =Table6[[#This Row],[Column2]]/$Z$25 -> 0.94 | AD31: 30 | AE31: =AE$28*$AD31 -> 30 | AF31: =AF$28*$AD31 -> 60 | AG31: =AG$28*$AD31 -> 90 | AH31: =AH$28*$AD31 -> 120 | AI31: =AI$28*$AD31 -> 150
S32: Jun | T32: 90000 | U32: 28000 | V32: =SUM(T32,U32) -> 118000 | Y32: Marie | Z32: 82 | AA32: =Table6[[#This Row],[Column2]]/$Z$25 -> 0.82 | AD32: 40 | AE32: =AE$28*$AD32 -> 40 | AF32: =AF$28*$AD32 -> 80 | AG32: =AG$28*$AD32 -> 120 | AH32: =AH$28*$AD32 -> 160 | AI32: =AI$28*$AD32 -> 200
S33: Jul | T33: 100000 | U33: 30000 | V33: =SUM(T33,U33) -> 130000 | Y33: Riya | Z33: 73 | AA33: =Table6[[#This Row],[Column2]]/$Z$25 -> 0.73 | AD33: 50 | AE33: =AE$28*$AD33 -> 50 | AF33: =AF$28*$AD33 -> 100 | AG33: =AG$28*$AD33 -> 150 | AH33: =AH$28*$AD33 -> 200 | AI33: =AI$28*$AD33 -> 250
S34: Aug | T34: 30000 | U34: 9000 | V34: =SUM(T34,U34) -> 39000 | Y34: Ariana | Z34: 96 | AA34: =Table6[[#This Row],[Column2]]/$Z$25 -> 0.96

Sheet Sheet2
B3: Product id | C3: Product Name | D3: Qty | E3: Price | I3: Product ID | J3: Product Name | K3: Qty | L3: Price
B4: 1001 | C4: Phone | D4: 40 | E4: 40000 | I4: 1004 | J4: =LOOKUP(I4,B3:C14) -> Sound Box
B5: 1002 | C5: Laptop | D5: 20 | E5: 50000 | I5: 1008 | J5: =VLOOKUP(I5,B3:E14,2,0) -> Dish washer | K5: =VLOOKUP(J5,C3:F14,2,0) -> 20 | L5: =VLOOKUP(K5,D3:G14,2,0) -> 50000
B6: 1003 | C6: TV | D6: 20 | E6: 50000
B7: 1004 | C7: Sound Box | D7: 10 | E7: 20000
B8: 1005 | C8: Refrigerator | D8: 20 | E8: 25000 | N8: Customer ID | O8: Policy ID | P8: Product ID | Q8: Premium | U8: Customer ID | V8: Name | W8: Gender | X8: Age | Y8: City | Z8: Vintage(In Months) | AC8: Name | AD8: Gender | AE8: Age | AF8: City | AJ8: Product ID | AK8: 1001 | AL8: 1002 | AM8: 1003 | AN8: 1004 | AO8: 1005 | AP8: 1006 | AQ8: 1007 | AR8: 1008
B9: 1006 | C9: Washing Machine | D9: 15 | E9: 25000 | N9: 1 | O9: 4010 | P9: 4 | Q9: 5000 | U9: 1 | V9: Niki | W9: F | X9: 19 | Y9: Seoul | Z9: 7 | AC9: =VLOOKUP(N9,U8:Z20,2,0) -> Niki | AD9: =VLOOKUP(N9,U8:Z20,3,0) -> F | AE9: =VLOOKUP(U9,U8:Z20,4,0) -> 19 | AF9: =VLOOKUP(U9,U8:Z20,5,0) -> Seoul | AJ9: Product Name | AK9: Phone | AL9: Tv | AM9: Soundbox | AN9: Refrigerator | AO9: Drone | AP9: Wasinh Machine | AQ9: Hair Drier | AR9: Vaccum Cleaner
B10: 1007 | C10: Hair Drier | D10: 60 | E10: 2000 | N10: 2 | O10: 2310 | P10: 2 | Q10: 2000 | U10: 2 | V10: Shreya | W10: F | X10: 17 | Y10: Gangnam | Z10: 7 | AC10: =VLOOKUP(N10,U9:Z21,2,0) -> Shreya | AD10: =VLOOKUP(N10,U9:Z21,3,0) -> F | AE10: =VLOOKUP(U10,U9:Z21,4,0) -> 17 | AF10: =VLOOKUP(U10,U9:Z21,5,0) -> Gangnam | AJ10: Qty | AK10: 100 | AL10: 20 | AM10: 20 | AN10: 15 | AO10: 50 | AP10: 20 | AQ10: 100 | AR10: 20
B11: 1008 | C11: Dish washer | D11: 20 | E11: 15000 | N11: 3 | O11: 1010 | P11: 1 | Q11: 6000 | U11: 3 | V11: Vaishnavi | W11: F | X11: 20 | Y11: Daegu | Z11: 12 | AC11: =VLOOKUP(N11,U10:Z22,2,0) -> Vaishnavi | AD11: =VLOOKUP(N11,U10:Z22,3,0) -> F | AE11: =VLOOKUP(U11,U10:Z22,4,0) -> 20 | AF11: =VLOOKUP(U11,U10:Z22,5,0) -> Daegu | AJ11: Price | AK11: 50000 | AL11: 70000 | AM11: 15000 | AN11: 20000 | AO11: 15000 | AP11: 15000 | AQ11: 2000 | AR11: 5000
B12: 1009 | C12: Vaccum Cleaner | D12: 10 | E12: 5000 | N12: 4 | O12: 3140 | P12: 1 | Q12: 4000 | U12: 4 | V12: Celestine | W12: F | X12: 19 | Y12: Busan | Z12: 7 | AC12: =VLOOKUP(N12,U11:Z23,2,0) -> Celestine | AD12: =VLOOKUP(N12,U11:Z23,3,0) -> F | AE12: =VLOOKUP(U12,U11:Z23,4,0) -> 19 | AF12: =VLOOKUP(U12,U11:Z23,5,0) -> Busan | AT12: Search product Details
B13: 1010 | C13: Print Machine | D13: 20 | E13: 5000 | N13: 5 | O13: 4350 | P13: 1 | Q13: 7000 | U13: 5 | V13: Rahila | W13: F | X13: 21 | Y13: Melbourne | Z13: 8 | AC13: =VLOOKUP(N13,U12:Z24,2,0) -> Rahila | AD13: =VLOOKUP(N13,U12:Z24,3,0) -> F | AE13: =VLOOKUP(U13,U12:Z24,4,0) -> 21 | AF13: =VLOOKUP(U13,U12:Z24,5,0) -> Melbourne | AT13: Product ID | AU13: Product Name | AV13: QTY | AW13: Price
B14: 1011 | C14: Drone | D14: 15 | E14: 4000 | N14: 6 | O14: 5120 | P14: 3 | Q14: 9000 | U14: 6 | V14: Liyan | W14: M | X14: 12 | Y14: Paris | Z14: 9 | AC14: =VLOOKUP(N14,U13:Z25,2,0) -> Liyan | AD14: =VLOOKUP(N14,U13:Z25,3,0) -> M | AE14: =VLOOKUP(U14,U13:Z25,4,0) -> 12 | AF14: =VLOOKUP(U14,U13:Z25,5,0) -> Paris | AT14: 1002 | AU14: =HLOOKUP(AT14,AJ8:AR11,2,0) -> Tv | AV14: =HLOOKUP(AT14,AJ8:AR11,3,0) -> 20 | AW14: =HLOOKUP(AT14,AJ8:AR11,4,0) -> 70000
N15: 7 | O15: 6789 | P15: 1 | Q15: 3000 | U15: 7 | V15: Preeti | W15: F | X15: 14 | Y15: Canada | Z15: 6 | AC15: =VLOOKUP(N15,U14:Z26,2,0) -> Preeti | AD15: =VLOOKUP(N15,U14:Z26,3,0) -> F | AE15: =VLOOKUP(U15,U14:Z26,4,0) -> 14 | AF15: =VLOOKUP(U15,U14:Z26,5,0) -> Canada
N16: 8 | O16: 1234 | P16: 2 | Q16: 2500 | U16: 8 | V16: Kiran | W16: M | X16: 12 | Y16: Macau | Z16: 8 | AC16: =VLOOKUP(N16,U15:Z27,2,0) -> Kiran | AD16: =VLOOKUP(N16,U15:Z27,3,0) -> M | AE16: =VLOOKUP(U16,U15:Z27,4,0) -> 12 | AF16: =VLOOKUP(U16,U15:Z27,5,0) -> Macau
N17: 9 | O17: 4321 | P17: 1 | Q17: 100 | U17: 9 | V17: Ayisha | W17: F | X17: 22 | Y17: Tokyo | Z17: 6 | AC17: =VLOOKUP(N17,U16:Z28,2,0) -> Ayisha | AD17: =VLOOKUP(N17,U16:Z28,3,0) -> F | AE17: =VLOOKUP(U17,U16:Z28,4,0) -> 22 | AF17: =VLOOKUP(U17,U16:Z28,5,0) -> Tokyo
N18: 10 | O18: 6123 | P18: 1 | Q18: 3500 | U18: 10 | V18: Harsha | W18: M | X18: 15 | Y18: Chicago | Z18: 9 | AC18: =VLOOKUP(N18,U17:Z29,2,0) -> Harsha | AD18: =VLOOKUP(N18,U17:Z29,3,0) -> M | AE18: =VLOOKUP(U18,U17:Z29,4,0) -> 15 | AF18: =VLOOKUP(U18,U17:Z29,5,0) -> Chicago
N19: 11 | O19: 5213 | P19: 4 | Q19: 4250 | U19: 11 | V19: Varsha | W19: F | X19: 23 | Y19: Incheon | Z19: 7 | AC19: =VLOOKUP(N19,U18:Z30,2,0) -> Varsha | AD19: =VLOOKUP(N19,U18:Z30,3,0) -> F | AE19: =VLOOKUP(U19,U18:Z30,4,0) -> 23 | AF19: =VLOOKUP(U19,U18:Z30,5,0) -> Incheon
N20: 12 | O20: 6987 | P20: 1 | Q20: 6000 | U20: 12 | V20: Vinay | W20: M | X20: 13 | Y20: NYC | Z20: 8 | AC20: =VLOOKUP(N20,U19:Z31,2,0) -> Vinay | AD20: =VLOOKUP(N20,U19:Z31,3,0) -> M | AE20: =VLOOKUP(U20,U19:Z31,4,0) -> 13 | AF20: =VLOOKUP(U20,U19:Z31,5,0) -> NYC

Sheet Sheet1
A1: STUDENT DETAILS
A2: FIRST NAME | B2: LAST NAME | C2: MARKS 1 | D2: MARKS 2 | E2: TOTAL | F2: AVERAGE
A3: AYISHA | B3: ASHRAF | C3: 95 | D3: 98 | E3: =SUM(C3:D3) -> 193 | F3: =AVERAGE(C3:D3) -> 96.5
A4: RAHILA | C4: 85 | D4: 85 | E4: =SUM(C4:D4) -> 170 | F4: =AVERAGE(C4:D4) -> 85
A5: VARSHA | B5: S | C5: 85 | D5: 94 | E5: =SUM(C5:D5) -> 179 | F5: =AVERAGE(C5:D5) -> 89.5
A6: VAISHNAVI | B6: SAWANTH | C6: 88 | D6: 91 | E6: =SUM(C6:D6) -> 179 | F6: =AVERAGE(C6:D6) -> 89.5
A7: GAYATRI | B7: GOND | C7: 89 | D7: 94 | E7: =SUM(C7:D7) -> 183 | F7: =AVERAGE(C7:D7) -> 91.5
A8: MAXIMUM MARKS = | C8: =MAX(C3:C7) -> 95 | D8: =MAX(D3:D7) -> 98 | E8: =MAX(E3:E7) -> 193
A9: MINIMUM MARKS = | C9: =MIN(C3:C8) -> 85 | D9: =MIN(D3:D8) -> 85 | E9: =MIN(E3:E8) -> 170
H15: SI.No | I15: First Name | J15: Last Name | K15: Full Name | L15: Length of full name | M15: Salary | N15: Contact No | O15: Gender | P15: Projects | Q15: Project Start Date | R15: Project End Date | S15: Total Days | T15: Net Working Days
H16: 1 | I16: Ariana | J16: Grande | K16: =CONCATENATE(I16, J16) -> ArianaGrande | L16: =LEN(K16) -> 12 | M16: 15000 | N16: 8877552244 | O16: Female | P16: Positions | Q16: 44952 | R16: 44980 | S16: =DAYS360(Q16,R16) -> 27 | T16: =NETWORKDAYS(Q16,R16,4) -> 21
H17: 2 | I17: Billie | J17: Elish | K17: =CONCATENATE(I17,J17) -> BillieElish | L17: =LEN(K17) -> 11 | M17: 25000 | N17: 6677445588 | O17: Female | P17: Lonely | Q17: 44983 | R17: 45008 | S17: =DAYS360(Q17,R17) -> 27 | T17: =NETWORKDAYS(Q17,R17,4) -> 19
H18: 3 | I18: Camila | J18: Cabello | K18: =CONCATENATE(I18,J18) -> CamilaCabello | L18: =LEN(K18) -> 13 | M18: 17000 | N18: 7722443311 | O18: Female | P18: Bam Bam | Q18: 45011 | R18: 45039 | S18: =DAYS360(Q18,R18) -> 27 | T18: =NETWORKDAYS(Q18,R18,4) -> 20
H19: 4 | I19: Charlie | J19: Puth | K19: =CONCATENATE(I19,J19) -> CharliePuth | L19: =LEN(K19) -> 11 | M19: 18000 | N19: 5544882233 | O19: Male | P19: Light Switch | Q19: 45042 | R19: 45069 | S19: =DAYS360(Q19,R19) -> 27 | T19: =NETWORKDAYS(Q19,R19,4) -> 20
H20: 5 | I20: Conan | J20: Grey | K20: =CONCATENATE(I20,J20) -> ConanGrey | L20: =LEN(K20) -> 9 | M20: 21000 | N20: 3344882211 | O20: Male | P20: Maniac | Q20: 45072 | R20: 45100 | S20: =DAYS360(Q20,R20) -> 27 | T20: =NETWORKDAYS(Q20,R20,4) -> 21
H21: 6 | I21: Ed | J21: Sheeran | K21: =CONCATENATE(I21,J21) -> Ed Sheeran | L21: =LEN(K21) -> 10 | M21: 25000 | N21: 7722115544 | O21: Male | P21: Photography | Q21: 45103 | R21: 45130 | S21: =DAYS360(Q21,R21) -> 27 | T21: =NETWORKDAYS(Q21,R21,4) -> 20
H22: 7 | I22: Harry | J22: Style | K22: =CONCATENATE(I22,J22) -> HarryStyle | L22: =LEN(K22) -> 10 | M22: 18000 | N22: 9933442200 | O22: Male | P22: Adore You | Q22: 45133 | R22: 45161 | S22: =DAYS360(Q22,R22) -> 27 | T22: =NETWORKDAYS(Q22,R22,4) -> 21
H23: 8 | I23: Olivia | J23: Rodrigo | K23: =CONCATENATE(I23,J23) -> OliviaRodrigo | L23: =LEN(K23) -> 13 | M23: 30000 | N23: 8800110077 | O23: Female | P23: Driver License | Q23: 45164 | R23: 45192 | S23: =DAYS360(Q23,R23) -> 27 | T23: =NETWORKDAYS(Q23,R23,4) -> 20
H24: 9 | I24: Shawn | J24: Mendes | K24: =CONCATENATE(I24,J24) -> ShawnMendes | L24: =LEN(K24) -> 11 | M24: 25000 | N24: 3344992200 | O24: Male | P24: Treat You Better | Q24: 45195 | R24: 45222 | S24: =DAYS360(Q24,R24) -> 27 | T24: =NETWORKDAYS(Q24,R24,4) -> 20
H25: 10 | I25: Taylor | J25: Swift | K25: =CONCATENATE(I25,J25) -> Taylor Swift | L25: =LEN(K25) -> 12 | M25: 10000 | N25: 5544996633 | O25: Female | P25: Willow | Q25: 45225 | R25: 45253 | S25: =DAYS360(Q25,R25) -> 27 | T25: =NETWORKDAYS(Q25,R25,4) -> 21
N27: No of male = | O27: =COUNTIF(O16:O25,"MALE") -> 5
N28: No of Female= | O28: =COUNTIF(O16:O25,"FEMALE") -> 5
M30: Total salary of female = | O30: =SUMIFS(M16:M25,O16:O25,"Female") -> 97000
M31: Total salary of male = | O31: =SUMIFS(M16:M25,O16:O25,"Male") -> 107000

Sheet Sheet6
B6: S.NO | C6: PRODUCT | D6: PRICE | E6: QTY | F6: TOTAL SALES | G6: PURCHASE | H6: AVL QTY | K6: S.NO | L6: STUDENT | M6: SUB1 | N6: SUB2 | O6: SUB3 | P6: SUB4 | Q6: SUB5 | R6: TOTAL MARKS | S6: AVERAGE | W6: NAME | X6: B.SALARY | Y6: INVE 10% | Z6: T.A 12% | AA6: PF 8% | AB6: NET SALARY
B7: 1 | C7: Product 1 | D7: 400 | E7: 2 | F7: =E7*D7 -> 800 | G7: 3000 | H7: =G7-E7 -> 2998 | K7: 1 | L7: RAHILA | M7: 85 | N7: 76 | O7: 66 | P7: 88 | Q7: 75 | R7: =SUM(M7:Q7) -> 390 | S7: =R7/$S$15*100 -> 78 | W7: ALAN | X7: 22000 | Y7: 2200 | Z7: 2640 | AA7: 1760
B8: 2 | C8: Product 2 | D8: 300 | E8: 4 | F8: =E8*D8 -> 1200 | G8: 40000 | H8: =G8-E8 -> 39996 | K8: 2 | L8: AYISHA | M8: 99 | N8: 85 | O8: 74 | P8: 90 | Q8: 84 | R8: =SUM(M8:Q8) -> 432 | S8: =R8/$S$15*100 -> 86.4 | W8: BRENT | X8: 18000 | Y8: 1800 | Z8: 2160 | AA8: 1440
B9: 3 | C9: Product 3 | D9: 350 | E9: 30 | F9: 10500 | G9: 50000 | H9: =G9-E9 -> 49970 | K9: 3 | L9: VARSHA | M9: 75 | N9: 79 | O9: 62 | P9: 92 | Q9: 73 | R9: =SUM(M9:Q9) -> 381 | S9: =R9/$S$15*100 -> 76.2 | W9: PIERSON | X9: 30000 | Y9: 3000 | Z9: 3600 | AA9: 2400
B10: 4 | C10: Product 4 | D10: 450 | E10: 3 | F10: =E10*D10 -> 1350 | G10: 5000 | H10: =G10-E10 -> 4997 | K10: 4 | L10: VAISHNAVI | M10: 86 | N10: 90 | O10: 60 | P10: 89 | Q10: 88 | R10: =SUM(M10:Q10) -> 413 | S10: =R10/$S$15*100 -> 82.6 | W10: ANDREW | X10: 40000 | Y10: 4000 | Z10: 4800 | AA10: 3200
B11: 5 | C11: Product 5 | D11: 800 | E11: 4 | F11: =E11*D11 -> 3200 | G11: 40000 | H11: =G11-E11 -> 39996 | K11: 5 | L11: GAYATRI | M11: 91 | N11: 80 | O11: 70 | P11: 87 | Q11: 89 | R11: =SUM(M11:Q11) -> 417 | S11: =R11/$S$15*100 -> 83.4 | W11: EMMA | X11: 20000 | Y11: 2000 | Z11: 2400 | AA11: 1600
B12: 6 | C12: Product 6 | D12: 1000 | E12: 40 | F12: 40000 | G12: 15000 | H12: =G12-E12 -> 14960 | W12: GABRIEL | X12: 50000 | Y12: 5000 | Z12: 6000 | AA12: 4000
D15: TOTAL AMOUNT = | F15: =SUM(F7:F12) -> 57050 | R15: TOTAL MARKS | S15: 500
